chainsim_sdk/__init__.py
chainsim_sdk/client.py
chainsim_sdk/client_types.py
chainsim_sdk/constants.py
chainsim_sdk/exceptions.py
chainsim_sdk/schemes.py
chainsim_sdk/interfaces/__init__.py
chainsim_sdk/interfaces/csim_client.py
chainsim_sdk_python-0.1.1.dist-info/METADATA
chainsim_sdk_python-0.1.1.dist-info/WHEEL
chainsim_sdk_python-0.1.1.dist-info/licenses/LICENSE
chainsim_sdk_python-0.1.1.dist-info/RECORD
