Metadata-Version: 2.4
Name: chainsim-sdk-python
Version: 0.1.1
Summary: SDK python package for Chainsim
License:                                  Apache License
License-File: LICENSE
Requires-Python: >=3.11
Requires-Dist: aiohttp>=3.12.15
Requires-Dist: certifi>=2025.8.3
